channels/__init__.py
channels/exceptions.py
channels/types.py
channels/backends/__init__.py
channels/backends/base.py
channels/backends/hipchat.py
channels/backends/slack.py
channels/backends/twitter.py
channels/backends/yo.py
django_channels-0.7.0.dist-info/DESCRIPTION.rst
django_channels-0.7.0.dist-info/METADATA
django_channels-0.7.0.dist-info/RECORD
django_channels-0.7.0.dist-info/WHEEL
django_channels-0.7.0.dist-info/metadata.json
django_channels-0.7.0.dist-info/pbr.json
django_channels-0.7.0.dist-info/top_level.txt
